qsys/classes.py
qsys/helpers.py
qsys-0.0.4.dist-info/LICENSE
qsys-0.0.4.dist-info/METADATA
qsys-0.0.4.dist-info/WHEEL
qsys-0.0.4.dist-info/top_level.txt
qsys-0.0.4.dist-info/RECORD
