Metadata-Version: 2.1
Name: qsys
Version: 0.0.4
Summary: Python QSYS QRC Wrapper
Home-page: https://github.com/mghelton/qsys
Author: Gage Helton
Author-email: gagehelton@gmail.com
License: UNKNOWN
Platform: UNKNOWN
Classifier: Programming Language :: Python :: 3
Classifier: License :: OSI Approved :: MIT License
Classifier: Operating System :: OS Independent
